{
    "MBAX6271": {
        "campus": "Sydney ",
        "conditions": "Conditions for Enrolment Must be enrolled in Program 8355, 8625, 8616, 5950, 5457, 7315, 7333, 8345 or 8350 ",
        "equivalent": [],
        "excluded": [],
        "faculty": " UNSW Business School",
        "handbook": "http://www.handbook.unsw.edu.au/postgraduate/courses/2021/MBAX6271.html",
        "level": "Postgraduate ",
        "name": "Approaches to Change",
        "school": " AGSM MBA Programs",
        "terms": "Term 1, Term 3 ",
        "timetable": "http://timetable.unsw.edu.au/2021/MBAX6271.html",
        "uoc": "6"
    },
    "MBAX6272": {
        "campus": "Sydney ",
        "conditions": "Conditions for Enrolment Pre-enrolled in 7315, 8616 or 8625 ",
        "equivalent": [],
        "excluded": [
            "MNGT6211"
        ],
        "faculty": " UNSW Business School",
        "handbook": "http://www.handbook.unsw.edu.au/postgraduate/courses/2021/MBAX6272.html",
        "level": "Postgraduate ",
        "name": "Change Skills",
        "school": " AGSM MBA Programs",
        "terms": "Term 2 ",
        "timetable": "http://timetable.unsw.edu.au/2021/MBAX6272.html",
        "uoc": "6"
    },
    "MBAX6274": {
        "campus": "Sydney ",
        "conditions": "Conditions for Enrolment Pre-requisite MNGT6271 or MBAX6271 and enrolment in program 5950, 7315, 8355, 8616, 8625 ",
        "equivalent": [],
        "excluded": [],
        "faculty": " UNSW Business School",
        "handbook": "http://www.handbook.unsw.edu.au/postgraduate/courses/2021/MBAX6274.html",
        "level": "Postgraduate ",
        "name": "Systems for Change",
        "school": " AGSM MBA Programs",
        "terms": "Term 2 ",
        "timetable": "http://timetable.unsw.edu.au/2021/MBAX6274.html",
        "uoc": "6"
    },
    "MBAX9101": {
        "campus": "Sydney ",
        "conditions": "Conditions for Enrolment Must be enrolled in Program 8355, 8625, 8616, 5950, 5457, 7315, 7333, 8345 or 8350 ",
        "equivalent": [],
        "excluded": [],
        "faculty": " UNSW Business School",
        "handbook": "http://www.handbook.unsw.edu.au/postgraduate/courses/2021/MBAX9101.html",
        "level": "Postgraduate ",
        "name": "Project Management",
        "school": " AGSM MBA Programs",
        "terms": "Term 1, Term 2, Term 3 ",
        "timetable": "http://timetable.unsw.edu.au/2021/MBAX9101.html",
        "uoc": "6"
    },
    "MBAX9114": {
        "campus": "Sydney ",
        "conditions": [],
        "equivalent": [
            "GBAT9114",
            "MNGT5251",
            "MNGT6251"
        ],
        "excluded": [],
        "faculty": " UNSW Business School",
        "handbook": "http://www.handbook.unsw.edu.au/postgraduate/courses/2021/MBAX9114.html",
        "level": "Postgraduate ",
        "name": "Marketing Management",
        "school": " AGSM MBA Programs",
        "terms": "Term 1, Term 2, Term 3 ",
        "timetable": "http://timetable.unsw.edu.au/2021/MBAX9114.html",
        "uoc": "6"
    },
    "MBAX9120": {
        "campus": "Sydney ",
        "conditions": [],
        "equivalent": [
            "GBAT9120",
            "MNGT5211",
            "MNGT6210"
        ],
        "excluded": [],
        "faculty": " UNSW Business School",
        "handbook": "http://www.handbook.unsw.edu.au/postgraduate/courses/2021/MBAX9120.html",
        "level": "Postgraduate ",
        "name": "Accounting and Financial Management",
        "school": " AGSM MBA Programs",
        "terms": "Term 1, Term 2, Term 3 ",
        "timetable": "http://timetable.unsw.edu.au/2021/MBAX9120.html",
        "uoc": "6"
    },
    "MBAX9122": {
        "campus": "Sydney ",
        "conditions": [],
        "equivalent": [
            "GBAT9122",
            "MNGT5201",
            "MNGT6302"
        ],
        "excluded": [],
        "faculty": " UNSW Business School",
        "handbook": "http://www.handbook.unsw.edu.au/postgraduate/courses/2021/MBAX9122.html",
        "level": "Postgraduate ",
        "name": "Economics in Management Practice",
        "school": " AGSM MBA Programs",
        "terms": "Term 1, Term 2 ",
        "timetable": "http://timetable.unsw.edu.au/2021/MBAX9122.html",
        "uoc": "6"
    },
    "MBAX9123": {
        "campus": "Sydney ",
        "conditions": [],
        "equivalent": [
            "MNGT5221",
            "MNGT6321"
        ],
        "excluded": [],
        "faculty": " UNSW Business School",
        "handbook": "http://www.handbook.unsw.edu.au/postgraduate/courses/2021/MBAX9123.html",
        "level": "Postgraduate ",
        "name": "Corporate Finance",
        "school": " AGSM MBA Programs",
        "terms": "Term 1, Term 2, Term 3 ",
        "timetable": "http://timetable.unsw.edu.au/2021/MBAX9123.html",
        "uoc": "6"
    },
    "MBAX9125": {
        "campus": "Sydney ",
        "conditions": "Conditions for Enrolment Must be enrolled in Program 8355, 8625, 8616, 5950, 5457, 7315, 7333, 8345 or 8350 ",
        "equivalent": [
            "GBAT9125",
            "MNGT6275"
        ],
        "excluded": [],
        "faculty": " UNSW Business School",
        "handbook": "http://www.handbook.unsw.edu.au/postgraduate/courses/2021/MBAX9125.html",
        "level": "Postgraduate ",
        "name": "Managing People & Organisations",
        "school": " AGSM MBA Programs",
        "terms": "Term 1, Term 2, Term 3 ",
        "timetable": "http://timetable.unsw.edu.au/2021/MBAX9125.html",
        "uoc": "6"
    },
    "MBAX9131": {
        "campus": "Sydney ",
        "conditions": "Conditions for Enrolment Prerequisite: must be enrolled in 8625 or 8355 ",
        "equivalent": [
            "GBAT9131"
        ],
        "excluded": [],
        "faculty": " UNSW Business School",
        "handbook": "http://www.handbook.unsw.edu.au/postgraduate/courses/2021/MBAX9131.html",
        "level": "Postgraduate ",
        "name": "Leadership",
        "school": " AGSM MBA Programs",
        "terms": "Term 1, Term 2, Term 3 ",
        "timetable": "http://timetable.unsw.edu.au/2021/MBAX9131.html",
        "uoc": "6"
    },
    "MBAX9132": {
        "campus": "Sydney ",
        "conditions": "Conditions for Enrolment Not enrolled in program 8355 ",
        "equivalent": [],
        "excluded": [],
        "faculty": " UNSW Business School",
        "handbook": "http://www.handbook.unsw.edu.au/postgraduate/courses/2021/MBAX9132.html",
        "level": "Postgraduate ",
        "name": "Intrapreneurship",
        "school": " AGSM MBA Programs",
        "terms": "Term 1, Term 2, Term 3 ",
        "timetable": "http://timetable.unsw.edu.au/2021/MBAX9132.html",
        "uoc": "6"
    },
    "MBAX9135": {
        "campus": "Sydney ",
        "conditions": "Conditions for Enrolment Must be enrolled in Program 8355, 8625, 8616, 5950, 5457, 7315, 7333, 8345 or 8350 ",
        "equivalent": [
            "GBAT9135",
            "MNGT5232",
            "MNGT6232"
        ],
        "excluded": [],
        "faculty": " UNSW Business School",
        "handbook": "http://www.handbook.unsw.edu.au/postgraduate/courses/2021/MBAX9135.html",
        "level": "Postgraduate ",
        "name": "Business Analytics",
        "school": " AGSM MBA Programs",
        "terms": "Term 1, Term 3 ",
        "timetable": "http://timetable.unsw.edu.au/2021/MBAX9135.html",
        "uoc": "6"
    },
    "MBAX9137": {
        "campus": "Sydney ",
        "conditions": "Conditions for Enrolment Prerequisites: (MNGT6321 OR MBAX9123 OR GBAT9123 OR MNGT5221) AND (MNGT6210 OR MBAX9120 OR GBAT9120 OR MNGT5211) ",
        "equivalent": [],
        "excluded": [],
        "faculty": " UNSW Business School",
        "handbook": "http://www.handbook.unsw.edu.au/postgraduate/courses/2021/MBAX9137.html",
        "level": "Postgraduate ",
        "name": "Advanced Finance",
        "school": " AGSM MBA Programs",
        "terms": "Term 1 ",
        "timetable": "http://timetable.unsw.edu.au/2021/MBAX9137.html",
        "uoc": "6"
    },
    "MBAX9138": {
        "campus": "Sydney ",
        "conditions": "Conditions for Enrolment Prerequisites: (MNGT6321 OR MBAX9123 OR GBAT9123 OR MNGT5221) AND (MNGT6210 OR MBAX9120 OR GBAT9120 OR MNGT5211) ",
        "equivalent": [],
        "excluded": [],
        "faculty": " UNSW Business School",
        "handbook": "http://www.handbook.unsw.edu.au/postgraduate/courses/2021/MBAX9138.html",
        "level": "Postgraduate ",
        "name": "Financial Analysis",
        "school": " AGSM MBA Programs",
        "terms": "Term 2 ",
        "timetable": "http://timetable.unsw.edu.au/2021/MBAX9138.html",
        "uoc": "6"
    },
    "MBAX9140": {
        "campus": "Sydney ",
        "conditions": "Conditions for Enrolment Prerequisites: (MNGT6321 OR MBAX9123 OR GBAT9123 OR MNGT5221) AND (MNGT6210 OR MBAX9120 OR GBAT9120 OR MNGT5211) ",
        "equivalent": [],
        "excluded": [],
        "faculty": " UNSW Business School",
        "handbook": "http://www.handbook.unsw.edu.au/postgraduate/courses/2021/MBAX9140.html",
        "level": "Postgraduate ",
        "name": "Global Finance",
        "school": " AGSM MBA Programs",
        "terms": "Term 1 ",
        "timetable": "http://timetable.unsw.edu.au/2021/MBAX9140.html",
        "uoc": "6"
    },
    "MBAX9141": {
        "campus": "Sydney ",
        "conditions": "Conditions for Enrolment Prerequisites: (MNGT6321 OR MBAX9123 OR GBAT9123 OR MNGT5221) AND (MNGT6210 OR MBAX9120 OR GBAT9120 OR MNGT5211) ",
        "equivalent": [],
        "excluded": [],
        "faculty": " UNSW Business School",
        "handbook": "http://www.handbook.unsw.edu.au/postgraduate/courses/2021/MBAX9141.html",
        "level": "Postgraduate ",
        "name": "Mergers and Acquisitions",
        "school": " AGSM MBA Programs",
        "terms": "Term 3 ",
        "timetable": "http://timetable.unsw.edu.au/2021/MBAX9141.html",
        "uoc": "6"
    },
    "MBAX9142": {
        "campus": "Sydney ",
        "conditions": "Conditions for Enrolment Prerequisites: (MNGT6321 OR MBAX9123 OR GBAT9123 OR MNGT5221) AND (MNGT6210 OR MBAX9120 OR GBAT9120 OR MNGT5211) ",
        "equivalent": [],
        "excluded": [],
        "faculty": " UNSW Business School",
        "handbook": "http://www.handbook.unsw.edu.au/postgraduate/courses/2021/MBAX9142.html",
        "level": "Postgraduate ",
        "name": "Financial Modelling",
        "school": " AGSM MBA Programs",
        "terms": "Term 2 ",
        "timetable": "http://timetable.unsw.edu.au/2021/MBAX9142.html",
        "uoc": "6"
    },
    "MBAX9143": {
        "campus": "Sydney ",
        "conditions": [],
        "equivalent": [],
        "excluded": [],
        "faculty": " UNSW Business School",
        "handbook": "http://www.handbook.unsw.edu.au/postgraduate/courses/2021/MBAX9143.html",
        "level": "Postgraduate ",
        "name": "Strategic Management",
        "school": " AGSM MBA Programs",
        "terms": "Term 1, Term 2, Term 3 ",
        "timetable": "http://timetable.unsw.edu.au/2021/MBAX9143.html",
        "uoc": "6"
    },
    "MBAX9150": {
        "campus": "Sydney ",
        "conditions": [],
        "equivalent": [],
        "excluded": [],
        "faculty": " UNSW Business School",
        "handbook": "http://www.handbook.unsw.edu.au/postgraduate/courses/2021/MBAX9150.html",
        "level": "Postgraduate ",
        "name": "Digital Innovation",
        "school": " AGSM MBA Programs",
        "terms": "Term 1, Term 2, Term 3 ",
        "timetable": "http://timetable.unsw.edu.au/2021/MBAX9150.html",
        "uoc": "6"
    },
    "MBAX9151": {
        "campus": "Sydney ",
        "conditions": [],
        "equivalent": [],
        "excluded": [],
        "faculty": " UNSW Business School",
        "handbook": "http://www.handbook.unsw.edu.au/postgraduate/courses/2021/MBAX9151.html",
        "level": "Postgraduate ",
        "name": "Law, Regulation & Ethics",
        "school": " AGSM MBA Programs",
        "terms": "Term 2, Term 3 ",
        "timetable": "http://timetable.unsw.edu.au/2021/MBAX9151.html",
        "uoc": "6"
    },
    "MBAX9152": {
        "campus": "Sydney ",
        "conditions": [],
        "equivalent": [],
        "excluded": [],
        "faculty": " UNSW Business School",
        "handbook": "http://www.handbook.unsw.edu.au/postgraduate/courses/2021/MBAX9152.html",
        "level": "Postgraduate ",
        "name": "Digital Strategy",
        "school": " AGSM MBA Programs",
        "terms": "Term 1, Term 2, Term 3 ",
        "timetable": "http://timetable.unsw.edu.au/2021/MBAX9152.html",
        "uoc": "6"
    },
    "MBAX9153": {
        "campus": "Sydney ",
        "conditions": [],
        "equivalent": [],
        "excluded": [
            "MNGT5180",
            "MNGT5370",
            "MNGT7495"
        ],
        "faculty": " UNSW Business School",
        "handbook": "http://www.handbook.unsw.edu.au/postgraduate/courses/2021/MBAX9153.html",
        "level": "Postgraduate ",
        "name": "Implementing Strategy",
        "school": " AGSM MBA Programs",
        "terms": "Term 1, Term 2, Term 3 ",
        "timetable": "http://timetable.unsw.edu.au/2021/MBAX9153.html",
        "uoc": "6"
    },
    "MBAX9154": {
        "campus": "Sydney ",
        "conditions": [],
        "equivalent": [],
        "excluded": [],
        "faculty": " UNSW Business School",
        "handbook": "http://www.handbook.unsw.edu.au/postgraduate/courses/2021/MBAX9154.html",
        "level": "Postgraduate ",
        "name": "Managing with Digital Technology",
        "school": " AGSM MBA Programs",
        "terms": "Term 1, Term 2, Term 3 ",
        "timetable": "http://timetable.unsw.edu.au/2021/MBAX9154.html",
        "uoc": "6"
    },
    "MBAX9155": {
        "campus": "Sydney ",
        "conditions": [],
        "equivalent": [],
        "excluded": [],
        "faculty": " UNSW Business School",
        "handbook": "http://www.handbook.unsw.edu.au/postgraduate/courses/2021/MBAX9155.html",
        "level": "Postgraduate ",
        "name": "Strategic Consulting Project",
        "school": " AGSM MBA Programs",
        "terms": "Term 1, Term 2, Term 3 ",
        "timetable": "http://timetable.unsw.edu.au/2021/MBAX9155.html",
        "uoc": "6"
    },
    "MBAX9202": {
        "campus": "Sydney ",
        "conditions": [],
        "equivalent": [],
        "excluded": [],
        "faculty": " UNSW Business School",
        "handbook": "http://www.handbook.unsw.edu.au/postgraduate/courses/2021/MBAX9202.html",
        "level": "Postgraduate ",
        "name": "Individual Research Project",
        "school": " AGSM MBA Programs",
        "terms": "Term 1, Term 2, Term 3 ",
        "timetable": "http://timetable.unsw.edu.au/2021/MBAX9202.html",
        "uoc": "6"
    }
}